wiktionary_de_parser/__init__.py
wiktionary_de_parser/assets/sprachcodes_iso639-1.txt
wiktionary_de_parser/config.py
wiktionary_de_parser/dump_processor/__init__.py
wiktionary_de_parser/models.py
wiktionary_de_parser/parser/__init__.py
wiktionary_de_parser/parser/parse_flexion.py
wiktionary_de_parser/parser/parse_hyphenation.py
wiktionary_de_parser/parser/parse_ipa.py
wiktionary_de_parser/parser/parse_language.py
wiktionary_de_parser/parser/parse_lemma.py
wiktionary_de_parser/parser/parse_meanings.py
wiktionary_de_parser/parser/parse_pos.py
wiktionary_de_parser/parser/parse_rhymes.py
wiktionary_de_parser/utils/meanings/tags.py
wiktionary_de_parser/utils/meanings/template_parser.py
wiktionary_de_parser/utils/meanings/wiki_list.py
wiktionary_de_parser-0.13.1.dist-info/LICENSE.txt
wiktionary_de_parser-0.13.1.dist-info/METADATA
wiktionary_de_parser-0.13.1.dist-info/WHEEL
wiktionary_de_parser-0.13.1.dist-info/RECORD
