Metadata-Version: 2.3
Name: wiktionary-de-parser
Version: 0.13.1
Summary: Extracts data from German Wiktionary dump files.
License: MIT
Keywords: wiktionary,xml,parser,data-extraction,german,nlp
Author: Gregor Weichbrodt
Author-email: gregorweichbrodt@gmail.com
Requires-Python: >=3.11,<4.0
Classifier: License :: OSI Approved :: MIT License
Classifier: Natural Language :: German
Classifier: Operating System :: OS Independent
Classifier: Programming Language :: Python :: 3
Classifier: Programming Language :: Python :: 3.11
Classifier: Programming Language :: Python :: 3.12
Classifier: Programming Language :: Python :: 3.13
Classifier: Programming Language :: Python :: 3.7
Classifier: Topic :: Text Processing :: Markup :: XML
Requires-Dist: lxml (>=5.1.0,<6.0.0)
Requires-Dist: mwparserfromhell (>=0.6.6,<0.7.0)
Requires-Dist: pydantic (>=2.6.0,<3.0.0)
Requires-Dist: requests (>=2.31.0,<3.0.0)
Requires-Dist: tqdm (>=4.66.1,<5.0.0)
Requires-Dist: wikitextparser (>=0.56.2,<0.57.0)
Project-URL: Bug Tracker, https://github.com/gambolputty/wiktionary-de-parser/issues
Project-URL: Homepage, https://github.com/gambolputty/wiktionary-de-parser
Project-URL: Repository, https://github.com/gambolputty/wiktionary-de-parser
